odoo8_addon_sale_order_type_sale_journal-8.0.1.0.0-py2.7-nspkg.pth
odoo_addons/sale_order_type_sale_journal/__openerp__.py
odoo_addons/sale_order_type_sale_journal/__init__.py
odoo_addons/sale_order_type_sale_journal/README.rst
odoo_addons/sale_order_type_sale_journal/models/sale_order.py
odoo_addons/sale_order_type_sale_journal/models/__init__.py
odoo_addons/sale_order_type_sale_journal/models/sale_order_type.py
odoo_addons/sale_order_type_sale_journal/views/sale_order_type_view.xml
odoo_addons/sale_order_type_sale_journal/tests/__init__.py
odoo_addons/sale_order_type_sale_journal/tests/test_sale_order_type.py
odoo_addons/sale_order_type_sale_journal/static/description/icon.png
odoo8_addon_sale_order_type_sale_journal-8.0.1.0.0.dist-info/top_level.txt
odoo8_addon_sale_order_type_sale_journal-8.0.1.0.0.dist-info/WHEEL
odoo8_addon_sale_order_type_sale_journal-8.0.1.0.0.dist-info/RECORD
odoo8_addon_sale_order_type_sale_journal-8.0.1.0.0.dist-info/metadata.json
odoo8_addon_sale_order_type_sale_journal-8.0.1.0.0.dist-info/DESCRIPTION.rst
odoo8_addon_sale_order_type_sale_journal-8.0.1.0.0.dist-info/METADATA
odoo8_addon_sale_order_type_sale_journal-8.0.1.0.0.dist-info/namespace_packages.txt
