Metadata-Version: 2.0
Name: odoo8-addon-sale-order-type-sale-journal
Version: 8.0.1.0.0
Summary: Link module between sale_order_type and sale_journal
Home-page: https://www.agilebg.com
Author: UNKNOWN
Author-email: UNKNOWN
License: AGPL-3
Platform: UNKNOWN
Requires-Dist: odoo (<9.0a,>=8.0a)
Requires-Dist: odoo8-addon-sale-order-type
Classifier: Programming Language :: Python :: 2.7
Classifier: Framework :: Odoo
Classifier: License :: OSI Approved :: GNU Affero General Public License v3
